dbclient/__init__.py
dbclientpy-0.0.3.dist-info/LICENSE
dbclientpy-0.0.3.dist-info/METADATA
dbclientpy-0.0.3.dist-info/WHEEL
dbclientpy-0.0.3.dist-info/top_level.txt
dbclientpy-0.0.3.dist-info/RECORD
