Metadata-Version: 2.1
Name: dbclientpy
Version: 0.0.3
Summary: An easy-to-use, flexible, and fast client for reading, writing, and manging your local database.
Project-URL: Homepage, https://github.com/placeholder102023/dbclient
Project-URL: Bug Tracker, https://github.com/placeholder102023/dbclient/issues
Classifier: Programming Language :: Python :: 3
Classifier: License :: OSI Approved :: MIT License
Classifier: Operating System :: OS Independent
Requires-Python: >=3.7
License-File: LICENSE
